geopops/__init__.py
geopops/census.py
geopops/config.json
geopops/config.py
geopops/download_data.py
geopops/geopops_starsim.py
geopops/ipfn.py
geopops/julia.py
geopops/geocore/geocorr2018_cbg_to_cbsa.csv
geopops/geocore/geocorr2018_cbg_urban_rural.csv
geopops/geocore/geocorr2018_puma_to_cbsa.csv
geopops/geocore/geocorr2018_puma_to_county.csv
geopops/geocore/geocorr2018_puma_urban_rural.csv
geopops/julia/CO.jl
geopops/julia/export_network.jl
geopops/julia/export_synthpop.jl
geopops/julia/fileutils.jl
geopops/julia/households.jl
geopops/julia/netw.jl
geopops/julia/schools.jl
geopops/julia/synthpop.jl
geopops/julia/test_netw.jl
geopops/julia/utils.jl
geopops/julia/workplaces.jl
geopops-0.1.1.post4.dist-info/METADATA
geopops-0.1.1.post4.dist-info/WHEEL
geopops-0.1.1.post4.dist-info/top_level.txt
geopops-0.1.1.post4.dist-info/RECORD
