Metadata-Version: 2.4
Name: geopops
Version: 0.1.1.post4
Summary: GeoPops
Requires-Python: >=3.11
Requires-Dist: curl-cffi>=0.13.0
Requires-Dist: geopandas
Requires-Dist: numpy<2.3
Requires-Dist: pandas>=2.3.2
Requires-Dist: requests>=2.32.5
Requires-Dist: shapely
Requires-Dist: starsim>=3.0.3
Requires-Dist: urllib3>=2.5.0
